{
    "volunteerList": [
        {
            "id": 10000,
            "name": "Peter",
            "major": "math",
            "year": 3
        },
        {
            "id": 10001,
            "name": "Jerry",
            "major": "biology",
            "year": 2
        },
        {
            "id": 10002,
            "name": "Matt",
            "major": "physics",
            "year": 3
        }
    ],
    "studentList":   [
      {
          "id": 10000,
          "name": "Kahan",
          "grade": 3,
          "Academic Confusion": {
                                    "id": 10000,
                                    "subject": "biology",
                                    "description": "aaa"
                                }
      },
      {
          "id": 10001,
          "name": "Mark",
          "grade": 4,
          "Academic Confusion": {
                                    "id": 10001,
                                    "subject": "math",
                                    "description": "bbb"
                                }
      },
      {
          "id": 10002,
          "name": "Carylon",
          "grade": 2,
          "Academic Confusion": {
                                    "id": 10002,
                                    "subject": "chemistry",
                                    "description": "ccc"
                                }
      }
    ],
    "questionList": [
      {
          "id": 10000,
          "subject": "biology",
          "description": "aaa"
      },
      {
          "id": 10001,
          "subject": "math",
          "description": "bbb"
      }
    ],
    "questionBeingAnsweredList":  [
      {
          "id": 10002,
          "subject": "chemistry",
          "description": "ccc"
      }
    ],
    "name": "Education Department"
}